{"1": [{"player": "Rei@DtS", "decks": ["https://shadowverse-portal.com/deckbuilder/create/1?hash=1.1.5zWm2.5zWm2.5zWm2.5zvAY.5zvAY.5zvAY.61jJY.61jJY.61jJY.61k2Q.61k2Q.61k2Q.61k32.61k32.61k32.61oCC.61oCC.61oCC.5zvvQ.5zvvQ.5zvvQ.61k2a.65YC2.68zBM.68zBM.68zBM.61qeS.61qeS.61qeS.61lmu.61lmu.61lmu.68_dS.68_dS.68_dS.659nE.659nE.659nE.61oww.61oww", "https://shadowverse-portal.com/deckbuilder/create/3?hash=1.3.61O4A.61O4A.5-gkQ.5-gkQ.5-gkQ.66NA2.66NA2.66NA2.6A6Qs.6A6Qs.6A6Qs.5-gka.5-gka.5-gka.5-gkk.5-gkk.5-gku.66IIA.66IIA.66IIA.6A8tG.6A8tG.6A8tG.66LT8.66LT8.61LeE.6A9bg.6A9bg.6A9bg.659nE.659nE.6A6RA.6A6RA.6A6RA.6A6RK.6A6RK.6A6RK.6ADlI.6ADlI.6ADlI"]}, {"player": "Show", "decks": ["https://shadowverse-portal.com/deckbuilder/create/5?hash=1.5.63E_G.63E_G.63E_G.63FiQ.63FiQ.63FiQ.65BUS.65BUS.65BUS.63Ezi.63Ezi.63Ezi.6Avi6.6Avi6.6Avi6.68_dm.68_dm.6737K.6737K.6AtGA.6AtGA.63Kb4.63Kb4.61PnY.61PnY.61PnY.6Avhy.6Avhy.63Kaw.63Kaw.63MII.63MII.63MII.63KbE.63KbE.63KbE.6AviG.6AviG.63Jsg.63Jsg", "https://shadowverse-portal.com/deckbuilder/create/3?hash=1.3.61O4A.61O4A.5-gkQ.5-gkQ.5-gkQ.66NA2.66NA2.66NA2.6A6Qs.6A6Qs.6A6Qs.5-gka.5-gka.5-gka.5-gkk.5-gkk.5-gkk.66IIA.66IIA.6A8tG.6A8tG.6A8tG.66LT8.66LT8.61LeE.6A9bg.6A9bg.6A9bg.659nE.6A6RA.6A6RA.6A6RA.62Uta.62Uta.6A6RK.6A6RK.6A6RK.6ADlI.6ADlI.6ADlI"]}], "2": [{"player": "temmy", "decks": ["https://shadowverse-portal.com/deckbuilder/create/5?hash=1.5.63E_G.63E_G.63E_G.63FiQ.63FiQ.63FiQ.61NLI.61NLI.65BUS.65BUS.65BUS.63Ezi.63Ezi.6Avi6.6Avi6.6Avi6.68_dm.68_dm.6737K.6737K.6AtGA.6AtGA.63Kb4.63Kb4.63Kb4.61PnY.61PnY.61PnY.6Avhy.6Avhy.63Kaw.63Kaw.63MII.63MII.63MII.63KbE.63KbE.63KbE.63Jsg.63Jsg", "https://shadowverse-portal.com/deckbuilder/create/1?hash=1.1.5zWm2.5zWm2.5zWm2.5zvAY.5zvAY.5zvAY.61jJY.61jJY.61jJY.61k2Q.61k2Q.61k2Q.61k32.61k32.61k32.61oCC.61oCC.61oCC.5zvvQ.5zvvQ.5zvvQ.65YC2.65YC2.68zBM.68zBM.68zBM.61qeS.61qeS.61qeS.61lmu.61lmu.61lmu.68_dS.68_dS.68_dS.659nE.659nE.659nE.61oww.61oww"]}, {"player": "\u305d\u3054\u308d\u3046", "decks": ["https://shadowverse-portal.com/deckbuilder/create/5?hash=1.5.61NLI.61NLI.61NLI.65BUS.65BUS.65BUS.68_dc.68_dc.68_dc.6736Y.6736Y.6736Y.5_RZQ.5_RZQ.5_RZQ.61KvW.61KvW.61KvW.68_dm.68_dm.6737K.6737K.6737K.63Kb4.63Kb4.6Aysw.6Aysw.6Aysw.63KbE.63KbE.63KbE.6AviG.6AviG.6AviG.63Jsg.63Jsg.63Jsg.6A-aI.6A-aI.6A-aI", "https://shadowverse-portal.com/deckbuilder/create/1?hash=1.1.5zWm2.5zWm2.5zWm2.5zvAY.5zvAY.5zvAY.61jJY.61jJY.61jJY.61k2Q.61k2Q.61k32.61k32.5zvAi.5zvAi.61oCC.61oCC.61oCC.65cLM.65cLM.65cLM.5zvvQ.5zvvQ.5zvvQ.65YC2.65YC2.61qeS.61qeS.61qeS.61lmu.61lmu.61Pni.61Pni.61Pni.65enI.65enI.65enI.65cL2.65cL2.65cL2"]}], "4": [{"player": "\u862d\u3055\u3093*PoB", "decks": ["https://shadowverse-portal.com/deckbuilder/create/1?hash=1.1.5zvAY.5zvAY.5zvAY.61jJY.61jJY.61jJY.61k2Q.61k2Q.61k2Q.61k32.61k32.61k32.5zvAi.5zvAi.61oCC.61oCC.61oCC.5zvvQ.5zvvQ.5zvvQ.65YC2.65YC2.61qeS.61qeS.61qeS.61lmu.61lmu.68_dS.68_dS.68_dS.65enI.61oww.61oww.61lmk.61lmk.69SwI.69SwI.61ox4.61ox4.61ox4", "https://shadowverse-portal.com/deckbuilder/create/4?hash=1.4.5_394.5_394.5_394.6AZjs.6AZjs.6AZjs.5_38w.5_38w.5_38w.62vkA.62vkA.62vkA.6AaSQ.6AaSQ.6AaSQ.62sZM.62sZM.62sZM.62v0O.62v0O.5_4sI.5_4sI.62u_S.62u_S.61NLm.61NLm.61NLm.6AY0A.6AY0A.6AY0A.694Vy.694Vy.694Vy.61SDy.61SDy.61SDy.61SE6.694Vo.694Vo.694Vo"]}, {"player": "xx13137xx", "decks": ["https://shadowverse-portal.com/deckbuilder/create/1?hash=1.1.5zWm2.5zWm2.5zWm2.5zvAY.5zvAY.5zvAY.61jJY.61jJY.61jJY.61k2Q.61k2Q.61k2Q.61k32.61k32.61k32.61oCC.61oCC.61oCC.65cLM.5zvvQ.5zvvQ.5zvvQ.65YC2.65YC2.68zBM.68zBM.68zBM.61qeS.61qeS.61qeS.61lmu.61lmu.68_dS.68_dS.68_dS.659nE.659nE.65enI.61oww.61oww", "https://shadowverse-portal.com/deckbuilder/create/3?hash=1.3.61O4A.61O4A.61O4A.5-gkQ.5-gkQ.5-gkQ.66NA2.66NA2.66NA2.6A6Qs.6A6Qs.6A6Qs.5-gka.5-gka.5-gka.5-gkk.5-gkk.5-gkk.62UtQ.66IIA.66IIA.66IIA.6A8tG.6A8tG.6A8tG.6A9bg.6A9bg.6A9bg.6A6RA.6A6RA.6A6RA.62Uta.62Uta.6A6RK.6A6RK.6A6RK.6ADlI.6ADlI.6ADlI.5-iRo"]}, {"player": "Leverage", "decks": ["https://shadowverse-portal.com/deckbuilder/create/1?hash=1.1.5zWm2.5zWm2.5zWm2.5zvAY.5zvAY.5zvAY.61jJY.61jJY.61jJY.61k2Q.61k2Q.61k2Q.61k32.61k32.61k32.61oCC.61oCC.61oCC.5zvvQ.5zvvQ.5zvvQ.68zBM.68zBM.68zBM.61qeS.61qeS.61qeS.61lmu.61lmu.61lmu.68_dS.68_dS.68_dS.659nE.659nE.65enI.65enI.65enI.61oww.61oww", "https://shadowverse-portal.com/deckbuilder/create/3?hash=1.3.5-gkQ.5-gkQ.5-gkQ.66NA2.66NA2.66NA2.6A6Qs.6A6Qs.6A6Qs.5-gka.5-gka.5-gka.5-gkk.5-gkk.5-gkk.66IIA.66IIA.66IIA.6A8tG.6A8tG.6A8tG.66LT8.66LT8.61LeE.61LeE.61LeE.6A9bg.6A9bg.6A9bg.659nE.659nE.6A6RA.6A6RA.6A6RA.6A6RK.6A6RK.6A6RK.6ADlI.6ADlI.6ADlI"]}, {"player": "\u3075\u305f\u307f*73", "decks": ["https://shadowverse-portal.com/deckbuilder/create/3?hash=1.3.61O4A.61O4A.61O4A.5-gkQ.5-gkQ.5-gkQ.66NA2.66NA2.66NA2.6A6Qs.6A6Qs.6A6Qs.5-gka.5-gka.5-gka.5-gkk.5-gkk.5-gkk.62UtQ.66IIA.66IIA.66IIA.6A8tG.6A8tG.6A8tG.6A9bg.6A9bg.6A9bg.6A6RA.6A6RA.6A6RA.62Uta.62Uta.6A6RK.6A6RK.6A6RK.6ADlI.6ADlI.6ADlI.5-iRo", "https://shadowverse-portal.com/deckbuilder/create/1?hash=1.1.5zWm2.5zWm2.5zWm2.5zvAY.5zvAY.5zvAY.61jJY.61jJY.61jJY.61k2Q.61k2Q.61k2Q.61k32.61k32.61k32.61oCC.61oCC.61oCC.65cLM.5zvvQ.5zvvQ.5zvvQ.65YC2.65YC2.68zBM.68zBM.68zBM.61qeS.61qeS.61qeS.61lmu.61lmu.68_dS.68_dS.68_dS.659nE.659nE.65enI.65enI.65enI"]}], "8": [{"player": "fuzz", "decks": ["https://shadowverse-portal.com/deckbuilder/create/4?hash=1.4.5zWm2.5zWm2.5zWm2.62sZ2.62sZ2.62sZ2.68_dc.68_dc.68_dc.62sac.62sac.62sac.66giC.66giC.66giC.62vkA.62vkA.62vkA.6AaSQ.6AaSQ.6AaSQ.68zBg.68zBg.68zBg.68_dm.68_dm.68_dm.66gi2.66gi2.66gi2.66j8S.66j8S.66j8S.659nE.659nE.62sZ-.62sZ-.62zty.62zty.62zty", "https://shadowverse-portal.com/deckbuilder/create/2?hash=1.2.5-Hb2.5-Hb2.5-Hb2.625lm.625lm.625lm.68_dc.68_dc.68_dc.625lc.625lc.625lc.628AI.628AI.628AI.65z2e.65z2e.65z2e.68zBg.68zBg.68zBg.625lI.625lI.625lI.5-K1I.5-K1I.5-K1I.69mSm.69mSm.69mSm.659nE.659nE.69rKo.69rKo.69rKo.62D36.62D36.62BLa.62BLa.62BLa"]}, {"player": "fuxtukun", "decks": ["https://shadowverse-portal.com/deckbuilder/create/3?hash=1.3.5-gkQ.5-gkQ.5-gkQ.66NA2.66NA2.66NA2.6A6Qs.6A6Qs.6A6Qs.5-gka.5-gka.5-gka.5-gkk.5-gkk.62UtQ.62UtQ.62UtQ.66IIA.66IIA.66IIA.6A8tG.6A8tG.6A8tG.66LT8.66LT8.66LT8.6A9bg.6A9bg.6A9bg.659nE.659nE.6A6RA.6A6RA.6A6RA.6A6RK.6A6RK.6A6RK.6ADlI.6ADlI.6ADlI", "https://shadowverse-portal.com/deckbuilder/create/7?hash=1.7.640Hy.640Hy.640Hy.60BfY.60BfY.60BfY.60COQ.60COQ.60COQ.60COa.60COa.63_os.63_os.642Eo.642Eo.642Eo.642Ey.642Ey.642Ey.640Xa.640Xa.640Xa.60E5y.60E5y.60E5y.6BjSI.6BjSI.6BjSI.67sO6.67sO6.67sO6.6BgWy.6BgWy.645Pw.645Pw.645Pw.67xlY.67xlY.67xlY.694Vo"]}, {"player": "FDG RiTen", "decks": ["https://shadowverse-portal.com/deckbuilder/create/3?hash=1.3.61O4A.61O4A.5-gkQ.5-gkQ.5-gkQ.66NA2.66NA2.66NA2.6A6Qs.6A6Qs.6A6Qs.5-gka.5-gka.5-gka.5-gkk.5-gkk.5-gkk.66IIA.66IIA.66IIA.6A8tG.6A8tG.6A8tG.66LT8.66LT8.6A9bg.6A9bg.6A9bg.659nE.6A6RA.6A6RA.6A6RA.62Uta.6A6RK.6A6RK.6A6RK.6ADlI.6ADlI.6ADlI.5-iRo", "https://shadowverse-portal.com/deckbuilder/create/1?hash=1.1.5zWm2.5zWm2.5zvAY.5zvAY.5zvAY.61jJY.61jJY.61jJY.61k2Q.61k2Q.61k2Q.61k32.61k32.61k32.61oCC.61oCC.61oCC.65cLM.5zvvQ.5zvvQ.5zvvQ.65YC2.65YC2.68zBM.68zBM.68zBM.61qeS.61qeS.61qeS.61lmu.61lmu.61lmu.68_dS.68_dS.68_dS.659nE.659nE.65enI.65enI.65enI"]}, {"player": "\u3086\u3093", "decks": ["https://shadowverse-portal.com/deckbuilder/create/3?hash=1.3.5-gkQ.5-gkQ.5-gkQ.66NA2.66NA2.66NA2.6A6Qs.6A6Qs.6A6Qs.5-gka.5-gka.5-gka.5-gkk.5-gkk.5-gkk.62UtQ.66IIA.66IIA.66IIA.6A8tG.6A8tG.6A8tG.66LT8.66LT8.61LeE.61LeE.6A9bg.6A9bg.6A9bg.659nE.659nE.6A6RA.6A6RA.6A6RA.6A6RK.6A6RK.6A6RK.6ADlI.6ADlI.6ADlI", "https://shadowverse-portal.com/deckbuilder/create/1?hash=1.1.5zWm2.5zWm2.5zWm2.5zvAY.5zvAY.5zvAY.61jJY.61jJY.61jJY.61k2Q.61k2Q.61k2Q.61k32.61k32.61k32.61oCC.61oCC.61oCC.5zvvQ.5zvvQ.5zvvQ.61k2a.65YC2.68zBM.68zBM.68zBM.61qeS.61qeS.fof0I.61lmu.61lmu.61lmu.68_dS.68_dS.68_dS.659nE.659nE.659nE.61oww.61oww"]}, {"player": "morizo", "decks": ["https://shadowverse-portal.com/deckbuilder/create/1?hash=1.1.5zWm2.5zWm2.5zWm2.5zvAY.5zvAY.5zvAY.61jJY.61jJY.61jJY.61k2Q.61k2Q.61k2Q.61k32.61k32.61k32.61oCC.61oCC.61oCC.65cLM.5zvvQ.5zvvQ.5zvvQ.65YC2.65YC2.68zBM.68zBM.68zBM.61qeS.61qeS.61qeS.61lmu.61lmu.68_dS.68_dS.68_dS.659nE.659nE.65enI.65enI.65enI", "https://shadowverse-portal.com/deckbuilder/create/3?hash=1.3.61O4A.61O4A.61O4A.5-gkQ.5-gkQ.5-gkQ.66NA2.66NA2.66NA2.6A6Qs.6A6Qs.6A6Qs.5-gka.5-gka.5-gka.5-gkk.5-gkk.5-gkk.62UtQ.66IIA.66IIA.66IIA.6A8tG.6A8tG.6A8tG.6A9bg.6A9bg.6A9bg.6A6RA.6A6RA.6A6RA.62Uta.62Uta.6A6RK.6A6RK.6A6RK.6ADlI.6ADlI.6ADlI.5-iRo"]}, {"player": "\u30ea\u30e5\u30fc\u30c9", "decks": ["https://shadowverse-portal.com/deckbuilder/create/6?hash=1.6.63dOW.63dOW.63dOW.63fr4.63fr4.63fr4.63dOg.63dOg.63dOg.67WPs.67WPs.67WPs.6BFgM.6BFgM.6BFgM.5_p-4.5_p-4.5_p-4.63e74.63e74.63e74.67WfK.68zBM.68zBM.68zBg.6BI6S.6BI6S.6BI6S.61LeE.61LeE.63gZA.63gZA.63gZA.68_dS.68_dS.659nE.659nE.5_pFW.5_pFW.5_pFW", "https://shadowverse-portal.com/deckbuilder/create/3?hash=1.3.5-gkQ.5-gkQ.5-gkQ.66NA2.66NA2.66NA2.6A6Qs.6A6Qs.6A6Qs.5-gka.5-gka.5-gka.5-gkk.5-gkk.62UtQ.62UtQ.62UtQ.66IIA.66IIA.66IIA.6A8tG.6A8tG.6A8tG.6A9bg.6A9bg.6A9bg.659nE.659nE.659nE.6A6RA.6A6RA.6A6RA.62Uta.62Uta.6A6RK.6A6RK.6A6RK.6ADlI.6ADlI.6ADlI"]}, {"player": "\u30ce\u30a2", "decks": ["https://shadowverse-portal.com/deckbuilder/create/1?hash=1.1.5zvAY.5zvAY.5zvAY.61jJY.61jJY.61jJY.61k2Q.61k2Q.61k2Q.61k32.61k32.61k32.61oCC.61oCC.61oCC.5zvvQ.5zvvQ.5zvvQ.65YC2.65YC2.68zBM.68zBM.61qeS.61qeS.61qeS.61lmu.61lmu.61lmu.68_dS.68_dS.61oww.61oww.61oww.61lmk.61lmk.69SwI.69SwI.61ox4.61ox4.61ox4", "https://shadowverse-portal.com/deckbuilder/create/3?hash=1.3.61O4A.61O4A.61O4A.5-gkQ.5-gkQ.5-gkQ.66NA2.66NA2.66NA2.5-gka.5-gka.5-gka.5-gkk.5-gkk.5-gkk.5-gku.5-gku.62UtQ.62UtQ.62XK8.62XK8.62XK8.66LT8.66LT8.62bTS.62bTS.62bTS.6A9bg.6A9bg.6A9bg.62Uta.62Uta.62Uta.5-glM.5-iRo.5-iRo.5-iRo.62Zm4.62Zm4.62Zm4"]}, {"player": "\u30ef\u30aa", "decks": ["https://shadowverse-portal.com/deckbuilder/create/3?hash=1.3.61O4A.61O4A.61O4A.5-gkQ.5-gkQ.5-gkQ.66NA2.66NA2.66NA2.6A6Qs.6A6Qs.6A6Qs.5-gka.5-gka.5-gka.5-gkk.5-gkk.5-gkk.66IIA.66IIA.66IIA.6A8tG.6A8tG.6A8tG.66LT8.6A9bg.6A9bg.6A9bg.6A6RA.6A6RA.6A6RA.62Uta.62Uta.6A6RK.6A6RK.6A6RK.6ADlI.6ADlI.6ADlI.5-iRo", "https://shadowverse-portal.com/deckbuilder/create/1?hash=1.1.5zWm2.5zWm2.5zWm2.5zvAY.5zvAY.5zvAY.61jJY.61jJY.61jJY.61k2Q.61k2Q.61k2Q.61k32.61k32.61k32.61oCC.61oCC.61oCC.5zvvQ.5zvvQ.5zvvQ.61k2a.68zBM.68zBM.68zBM.61qeS.61qeS.61qeS.61lmu.61lmu.61lmu.68_dS.68_dS.68_dS.659nE.659nE.65enI.65enI.61oww.61oww"]}], "crafts": [12, 1, 12, 2, 3, 1, 1, 0], "code": "195"}